dlock/__init__.py
dlock/__main__.py
dlock/cli.py
dlock/instructions.py
dlock/io.py
dlock/output.py
dlock/parsing.py
dlock/processing.py
dlock/py.typed
dlock/registry.py
dlock-0.2.dist-info/LICENSE
dlock-0.2.dist-info/METADATA
dlock-0.2.dist-info/NOTICE
dlock-0.2.dist-info/WHEEL
dlock-0.2.dist-info/entry_points.txt
dlock-0.2.dist-info/top_level.txt
dlock-0.2.dist-info/RECORD
