Metadata-Version: 2.1
Name: dlock
Version: 0.2
Summary: Locks your Docker dependencies
Home-page: https://github.com/akamai/dlock
Author: Miloslav Pojman
Author-email: mpojman@akamai.com
License: Apache License 2.0
Project-URL: Source Code, https://github.com/akamai/dlock
Keywords: Docker,Dockerfile,containers,dependencies,lock,locking,pinning,security,digest,hash
Platform: UNKNOWN
Classifier: Environment :: Console
Classifier: Intended Audience :: Developers
Classifier: Intended Audience :: Information Technology
Classifier: Intended Audience :: System Administrators
Classifier: License :: OSI Approved :: Apache Software License
Classifier: Programming Language :: Python
Classifier: Programming Language :: Python :: 3
Classifier: Programming Language :: Python :: 3.7
Classifier: Programming Language :: Python :: 3.8
Classifier: Programming Language :: Python :: 3.9
Classifier: Topic :: Security
Classifier: Topic :: Software Development
Classifier: Topic :: Software Development :: Build Tools
Classifier: Topic :: Utilities
Classifier: Typing :: Typed
Requires-Python: >=3.7
Requires-Dist: docker
Provides-Extra: dev
Requires-Dist: black ; extra == 'dev'
Requires-Dist: flake8 ; extra == 'dev'
Requires-Dist: isort ; extra == 'dev'
Requires-Dist: mypy ; extra == 'dev'
Requires-Dist: pytest ; extra == 'dev'
